MANIFEST.in
setup.py
tornado_cli/__init__.py
tornado_cli.egg-info/PKG-INFO
tornado_cli.egg-info/SOURCES.txt
tornado_cli.egg-info/dependency_links.txt
tornado_cli.egg-info/entry_points.txt
tornado_cli.egg-info/top_level.txt
tornado_cli/commands/__init__.py
tornado_cli/commands/base.py
tornado_cli/commands/help.py
tornado_cli/commands/startproject.py
tornado_cli/project_template/__init__.py
tornado_cli/project_template/app.py
tornado_cli/project_template/environment.py
tornado_cli/project_template/settings.py
tornado_cli/project_template/urls.py
tornado_cli/project_template/handlers/__init__.py
tornado_cli/project_template/handlers/base.py
tornado_cli/project_template/handlers/welcome.py
tornado_cli/project_template/logconfig/__init__.py
tornado_cli/project_template/logconfig/dictconfig.py
tornado_cli/project_template/logconfig/logconfig.py
tornado_cli/project_template/media/.empty
tornado_cli/project_template/templates/welcome.html
tornado_cli/project_template/tests/__init__.py
tornado_cli/project_template/tests/run_tests.py