Metadata-Version: 1.0
Name: tornado-cli
Version: 0.1
Summary: A command line interface helper for Tornado
Home-page: UNKNOWN
Author: Stuart Marsh
Author-email: stuart@beardygeek.com
License: MIT
Platform: UNKNOWN
